{
  "updated": "2026-06-16",
  "period": "9.–15. juni 2026 (siste 7 dager)",
  "target_kr_per_lead": 300,
  "counts": {
    "sporet": 33,
    "hentet": 17,
    "tomme_dvale": 7,
    "billing_flagg": 9
  },
  "totals": {
    "NOK": {
      "spend": 44793.52,
      "leads": 174,
      "kr_per_lead": 257.43,
      "aktive": 14
    }
  },
  "flags": [
    {
      "level": "red",
      "text": "Lillestrøm Tannhelse: kr 10 057 brukt, kun 2 leads (kr 5 029/lead). LP- og Tannbleking-kampanjene har 0 registrerte leads på kr 8 740 – sjekk pixel/skjema umiddelbart."
    },
    {
      "level": "red",
      "text": "Klinikkflow annonsekonto: kr 799/lead (7 leads på kr 5 596) – godt over kr 300-målet."
    },
    {
      "level": "red",
      "text": "Frøyd: kr 387/lead – over kr 300-målet."
    },
    {
      "level": "yellow",
      "text": "DC Wholesale (Dui Clinique): kr 1 574 brukt, 0 leads."
    },
    {
      "level": "yellow",
      "text": "Bailine Stavanger: kr 607 brukt, 0 leads."
    },
    {
      "level": "yellow",
      "text": "Alt pauset: Cranioklinikken, Bailine hovedkontor, Bailine Arendal annonsekonto."
    },
    {
      "level": "billing",
      "text": "9 kontoer med flagg: 2 UNSETTLED, 2 mangler betalingsmåte, 5 venter på MCP-utrulling."
    }
  ],
  "accounts": [
    {
      "name": "Lillestrøm Tannhelse",
      "id": "2480737008774788",
      "status": "aktiv",
      "spend": 10057.31,
      "leads": 2,
      "note": "LP- og Tannbleking-kampanjene: 0 registrerte leads på 8 740 kr – mulig pixel/tracking-problem",
      "campaigns": [
        {
          "name": "KF - Landing page - 549,-",
          "status": "aktiv",
          "spend": 6791.98,
          "leads": 0,
          "ctr": "4.17%",
          "cpc": 3.44
        },
        {
          "name": "KF - Tannbleking + Undersøkelse",
          "status": "aktiv",
          "spend": 1948.41,
          "leads": 0,
          "ctr": "0.70%",
          "cpc": 18.92
        },
        {
          "name": "<KF> Leadform full time 549,-",
          "status": "aktiv",
          "spend": 690.93,
          "leads": 1,
          "ctr": "0.96%",
          "cpc": 13.29
        },
        {
          "name": "Undersøkelse - ABO - NovVinnere",
          "status": "aktiv",
          "spend": 625.99,
          "leads": 1,
          "ctr": "1.87%",
          "cpc": 7.36
        }
      ],
      "kr_per_lead": 5028.65
    },
    {
      "name": "Klinikkflow annonsekonto",
      "id": "4459528394274918",
      "status": "aktiv",
      "spend": 5595.67,
      "leads": 7,
      "campaigns": [
        {
          "name": "Klinikkflow - Gratis Strategisamtale",
          "status": "aktiv",
          "spend": 5595.67,
          "leads": 7,
          "ctr": "1.75%",
          "cpc": 14.31
        }
      ],
      "kr_per_lead": 799.38
    },
    {
      "name": "Frøyd",
      "id": "310102620",
      "status": "aktiv",
      "spend": 5032.39,
      "leads": 13,
      "campaigns": [
        {
          "name": "Microneedling superoffer (KF)",
          "status": "aktiv",
          "spend": 3277.93,
          "leads": 8,
          "ctr": "2.71%",
          "cpc": 8.88
        },
        {
          "name": "Bio-Meso PDRN Glow (KF)",
          "status": "aktiv",
          "spend": 1754.46,
          "leads": 5,
          "ctr": "2.85%",
          "cpc": 7.1
        }
      ],
      "kr_per_lead": 387.11
    },
    {
      "name": "Nurdent",
      "id": "855555962141950",
      "status": "aktiv",
      "spend": 2988.32,
      "leads": 13,
      "note": "Undersøkelse 490 har mixed objektiv – leads ukjent",
      "campaigns": [
        {
          "name": "New Leads campaign",
          "status": "aktiv",
          "spend": 1926.35,
          "leads": 13,
          "ctr": "2.47%",
          "cpc": 6.25
        },
        {
          "name": "KF - Undersøkelse 490",
          "status": "aktiv",
          "spend": 1061.97,
          "leads": null,
          "ctr": "1.63%",
          "cpc": 7.93
        }
      ],
      "kr_per_lead": 229.87
    },
    {
      "name": "Glow to Go",
      "id": "1414745150338015",
      "status": "aktiv",
      "spend": 2823.81,
      "leads": 27,
      "note": "Ejal ny er link_click-objektiv (ikke lead)",
      "campaigns": [
        {
          "name": "KF - Skinbooster Ejal40",
          "status": "aktiv",
          "spend": 2111.87,
          "leads": 27,
          "ctr": "3.90%",
          "cpc": 4.34
        },
        {
          "name": "Ejal ny",
          "status": "aktiv",
          "spend": 711.94,
          "leads": null,
          "ctr": "2.31%",
          "cpc": 1.89
        }
      ],
      "kr_per_lead": 104.59
    },
    {
      "name": "My skin klinikk",
      "id": "1767124990772163",
      "status": "aktiv",
      "spend": 2782.23,
      "leads": 19,
      "campaigns": [
        {
          "name": "KF - Microneedling + LED - V3",
          "status": "aktiv",
          "spend": 2782.23,
          "leads": 19,
          "ctr": "2.09%",
          "cpc": 7.93
        }
      ],
      "kr_per_lead": 146.43
    },
    {
      "name": "Storhamar Bil",
      "id": "873090401637057",
      "status": "aktiv",
      "spend": 2685.82,
      "leads": 16,
      "campaigns": [
        {
          "name": "KF - Kommisjonssalg - V1",
          "status": "aktiv",
          "spend": 2685.82,
          "leads": 16,
          "ctr": "2.27%",
          "cpc": 5.81
        }
      ],
      "kr_per_lead": 167.86
    },
    {
      "name": "Cranioklinikken",
      "id": "1418993789293324",
      "status": "off",
      "spend": 2654.98,
      "leads": 7,
      "note": "Kampanje pauset",
      "campaigns": [
        {
          "name": "[KF] KAMPANJE (Intro 890,-) Leads",
          "status": "off",
          "spend": 2654.98,
          "leads": 7,
          "ctr": "3.15%",
          "cpc": 6.49
        }
      ],
      "kr_per_lead": 379.28
    },
    {
      "name": "Lumera Skin Clinic",
      "id": "746360314757056",
      "status": "aktiv",
      "spend": 2083.37,
      "leads": 11,
      "campaigns": [
        {
          "name": "KF Profhilo v1",
          "status": "aktiv",
          "spend": 2083.37,
          "leads": 11,
          "ctr": "2.71%",
          "cpc": 9.18
        }
      ],
      "kr_per_lead": 189.4
    },
    {
      "name": "Ake klinikk",
      "id": "1657659812232896",
      "status": "aktiv",
      "spend": 2041.55,
      "leads": 33,
      "campaigns": [
        {
          "name": "Osmotherm 21. v1 // KF",
          "status": "aktiv",
          "spend": 2041.55,
          "leads": 33,
          "ctr": "5.56%",
          "cpc": 2.68
        }
      ],
      "kr_per_lead": 61.87
    },
    {
      "name": "DC Wholesale (Dui Clinique)",
      "id": "1644801020074445",
      "status": "aktiv",
      "spend": 1574.49,
      "leads": 0,
      "note": "0 leads på 1 574 kr",
      "campaigns": [
        {
          "name": "DEP // KF",
          "status": "aktiv",
          "spend": 1574.49,
          "leads": 0,
          "ctr": "4.26%",
          "cpc": 7.83
        }
      ],
      "kr_per_lead": null
    },
    {
      "name": "Bioplasmaklinikk",
      "id": "1803528443943666",
      "status": "aktiv",
      "spend": 1389.0,
      "leads": 13,
      "campaigns": [
        {
          "name": "KF - PDRN Microneedling",
          "status": "aktiv",
          "spend": 1389.0,
          "leads": 13,
          "ctr": "3.70%",
          "cpc": 3.75
        }
      ],
      "kr_per_lead": 106.85
    },
    {
      "name": "Bailine hovedkontor",
      "id": "797054139242362",
      "status": "off",
      "spend": 1212.04,
      "leads": 3,
      "note": "Kampanje pauset",
      "campaigns": [
        {
          "name": "Nye Bailine klinikker-Juni 2026",
          "status": "off",
          "spend": 1212.04,
          "leads": 3,
          "ctr": "2.61%",
          "cpc": 7.72
        }
      ],
      "kr_per_lead": 404.01
    },
    {
      "name": "Bailine Stavanger",
      "id": "26246499",
      "status": "aktiv",
      "spend": 607.18,
      "leads": 0,
      "note": "0 leads på 607 kr",
      "campaigns": [
        {
          "name": "KF - Bailine Stavanger v1",
          "status": "aktiv",
          "spend": 607.18,
          "leads": 0,
          "ctr": "5.54%",
          "cpc": 2.89
        }
      ],
      "kr_per_lead": null
    },
    {
      "name": "Bailine Arendal annonsekonto",
      "id": "1346163396433367",
      "status": "off",
      "spend": 533.1,
      "leads": 6,
      "note": "Kampanje pauset",
      "campaigns": [
        {
          "name": "<KF> Figurforming introtime 450,-",
          "status": "off",
          "spend": 533.1,
          "leads": 6,
          "ctr": "4.15%",
          "cpc": 3.14
        }
      ],
      "kr_per_lead": 88.85
    },
    {
      "name": "Omsorgsgruppen Øst",
      "id": "2687347888130903",
      "status": "aktiv",
      "spend": 465.39,
      "leads": null,
      "note": "contact_website-objektiv – leads ikke målt",
      "campaigns": [
        {
          "name": "Ny Engasjement-kampanje",
          "status": "aktiv",
          "spend": 465.39,
          "leads": null,
          "ctr": "3.34%",
          "cpc": 3.08
        }
      ],
      "kr_per_lead": null
    },
    {
      "name": "Bodyflow Ad Account 2",
      "id": "2104248957054228",
      "status": "aktiv",
      "spend": 266.87,
      "leads": 4,
      "campaigns": [
        {
          "name": "KF Microneedling",
          "status": "aktiv",
          "spend": 136.03,
          "leads": 1,
          "ctr": "5.64%",
          "cpc": 3.09
        },
        {
          "name": "EM Muskel Stim <KF> 599,-",
          "status": "aktiv",
          "spend": 130.84,
          "leads": 3,
          "ctr": "5.47%",
          "cpc": 4.36
        }
      ],
      "kr_per_lead": 66.72
    }
  ],
  "tomme_dvale": [
    "HarmoniAkupunktur",
    "Vekst & Balanse Klinikken",
    "Medic Fot Annonsekonto",
    "Joachim Majambere",
    "Klinikk Tønsberg (Linda Rasmussen)",
    "Force of Beauty",
    "Lysaker Brygge Tannklinikk"
  ],
  "billing": [
    {
      "name": "Tannboden Brønnøysund",
      "reason": "UNSETTLED"
    },
    {
      "name": "Serene By Design",
      "reason": "UNSETTLED"
    },
    {
      "name": "Medic Fot Stokke",
      "reason": "mangler betalingsmåte"
    },
    {
      "name": "Annonsekonto 637967305134171",
      "reason": "mangler betalingsmåte"
    },
    {
      "name": "Annonsekonto 35409629",
      "reason": "MCP-utrulling"
    },
    {
      "name": "Elora klinikken",
      "reason": "MCP-utrulling"
    },
    {
      "name": "Bailine Arendal (USD)",
      "reason": "MCP-utrulling"
    },
    {
      "name": "Ro Massasje",
      "reason": "MCP-utrulling"
    },
    {
      "name": "Pimentel",
      "reason": "MCP-utrulling"
    }
  ]
}